timefops/__init__.py
timefops/_cli.py
timefops/_logger.py
timefops/timefops.py
timefops-0.3.dist-info/LICENSE.txt
timefops-0.3.dist-info/METADATA
timefops-0.3.dist-info/WHEEL
timefops-0.3.dist-info/entry_points.txt
timefops-0.3.dist-info/top_level.txt
timefops-0.3.dist-info/RECORD
