Metadata-Version: 2.1
Name: timefops
Version: 0.3
Summary: A cross-platform module for file operations based on time.
Home-page: https://github.com/stiftcast/timefops
Author: stiftcast
Author-email: stiftcast@gmail.com
License: GPLv3
Platform: UNKNOWN
Classifier: Development Status :: 4 - Beta
Classifier: Intended Audience :: Developers
Classifier: Intended Audience :: End Users/Desktop
Classifier: Intended Audience :: System Administrators
Classifier: License :: OSI Approved :: GNU General Public License v3 (GPLv3)
Classifier: Programming Language :: Python :: 3.7
Classifier: Programming Language :: Python :: 3.8
Classifier: Programming Language :: Python :: 3.9
Classifier: Operating System :: OS Independent
Classifier: Topic :: System :: Archiving :: Compression
Classifier: Topic :: System :: Filesystems
Requires-Python: >=3.7
Requires-Dist: colorama
Requires-Dist: pyzipper
